neuroclassify/__init__.py
neuroclassify/classifier.py
neuroclassify/utils.py
neuroclassify-3.1.dist-info/LICENSE
neuroclassify-3.1.dist-info/METADATA
neuroclassify-3.1.dist-info/WHEEL
neuroclassify-3.1.dist-info/top_level.txt
neuroclassify-3.1.dist-info/RECORD
