Metadata-Version: 2.1
Name: neuroclassify
Version: 3.1
Summary: A simple image classification package using deep learning.
Home-page: https://github.com/IMApurbo/neuroclassify
Author: AKM Korishee Apurbo
Author-email: bandinvisible8@gmail.com
Classifier: Programming Language :: Python :: 3
Classifier: License :: OSI Approved :: MIT License
Classifier: Programming Language :: Python :: 3.8
Classifier: Programming Language :: Python :: 3.9
Classifier: Programming Language :: Python :: 3.10
Classifier: Operating System :: OS Independent
Requires-Python: >=3.6
License-File: LICENSE
Requires-Dist: tensorflow>=2.0
Requires-Dist: numpy>=1.18.5
Requires-Dist: matplotlib>=3.0
Requires-Dist: Pillow>=7.0.0
Requires-Dist: scikit-learn>=0.23.2
